AUTHORS.rst
CONTRIBUTING.rst
HISTORY.rst
LICENSE
MANIFEST.in
README.rst
setup.py
nbdiff/__init__.py
nbdiff/commands.py
nbdiff/comparable.py
nbdiff/diff.py
nbdiff/merge.py
nbdiff/nbdiff.py
nbdiff/notebook_diff.py
nbdiff/notebook_parser.py
nbdiff.egg-info/PKG-INFO
nbdiff.egg-info/SOURCES.txt
nbdiff.egg-info/dependency_links.txt
nbdiff.egg-info/entry_points.txt
nbdiff.egg-info/not-zip-safe
nbdiff.egg-info/requires.txt
nbdiff.egg-info/top_level.txt
nbdiff/adapter/__init__.py
nbdiff/adapter/git_adapter.py
nbdiff/adapter/hg_adapter.py
nbdiff/adapter/vcs_adapter.py
nbdiff/server/__init__.py
nbdiff/server/local_server.py
nbdiff/server/remote_server.py
nbdiff/server/command/AboutUsCommand.py
nbdiff/server/command/ComparisonCommand.py
nbdiff/server/command/ContactUsCommand.py
nbdiff/server/command/DiffCommand.py
nbdiff/server/command/DiffURLCommand.py
nbdiff/server/command/FaqCommand.py
nbdiff/server/command/MergeCommand.py
nbdiff/server/command/MergeURLCommand.py
nbdiff/server/command/NotebookRequestCommand.py
nbdiff/server/command/ResourceRequestCommand.py
nbdiff/server/command/SaveNotebookCommand.py
nbdiff/server/command/UploadCommand.py
nbdiff/server/command/__init__.py
nbdiff/server/database/__init__.py
nbdiff/server/database/nbdiffModel.py
nbdiff/server/static/css/bootstrap.css
nbdiff/server/static/css/bootstrap.min.css
nbdiff/server/static/css/local.css
nbdiff/server/static/css/nbdiff.css
nbdiff/server/static/css/parent.css
nbdiff/server/static/css/style.css
nbdiff/server/static/css/upload.css
nbdiff/server/static/image/favicon.ico
nbdiff/server/static/image/glyphicons-halflings-white.png
nbdiff/server/static/image/glyphicons-halflings.png
nbdiff/server/static/image/logo.png
nbdiff/server/static/js/command.js
nbdiff/server/static/js/drag_drop.js
nbdiff/server/static/js/local.js
nbdiff/server/static/js/main.js
nbdiff/server/static/js/nbdiff.js
nbdiff/server/static/js/remote.js
nbdiff/server/static/js/upload.js
nbdiff/server/static/libraries/bootstrap.js
nbdiff/server/static/libraries/bootstrap.min.js
nbdiff/server/static/libraries/jquery-1.10.2.js
nbdiff/server/static/libraries/verify.notify.min.js
nbdiff/server/templates/ContactUs.html
nbdiff/server/templates/Error.html
