Metadata-Version: 1.1
Name: nbdiff
Version: 1.0.3
Summary: A tool for diffing and merging IPython Notebook files
Home-page: https://github.com/tarmstrong/nbdiff
Author: Tavish Armstrong
Author-email: tavisharmstrong@gmail.com
License: MIT
Keywords: nbdiff
Platform: UNKNOWN
Classifier: Development Status :: 2 - Pre-Alpha
Classifier: Intended Audience :: Developers
Classifier: License :: OSI Approved :: BSD License
Classifier: Natural Language :: English
Classifier: Programming Language :: Python :: 2
Classifier: Programming Language :: Python :: 2.6
Classifier: Programming Language :: Python :: 2.7
Classifier: Programming Language :: Python :: 3
Classifier: Programming Language :: Python :: 3.3
